src/__init__.py
src/__main__.py
src/annotate.py
src/arabidopsis_pfam.tsv
src/blacklist.tsv
src/extract.py
src/human_pfam.tsv
scanexitronlr-1.1.9.dist-info/LICENSE
scanexitronlr-1.1.9.dist-info/METADATA
scanexitronlr-1.1.9.dist-info/WHEEL
scanexitronlr-1.1.9.dist-info/entry_points.txt
scanexitronlr-1.1.9.dist-info/top_level.txt
scanexitronlr-1.1.9.dist-info/RECORD
