Metadata-Version: 2.1
Name: scanexitronlr
Version: 1.1.9
Summary: ScanExitronLR: a lightweight tool for the characterization and quantification of exitrons in long read RNA-seq data
Home-page: https://github.com/ylab/ScanExitronLR
Author: Josh Fry
Author-email: fryxx094@umn.edu
License: MIT
Classifier: License :: OSI Approved :: MIT License
Classifier: Operating System :: OS Independent
Classifier: Development Status :: 5 - Production/Stable
Classifier: Programming Language :: Python :: 3.7
Requires-Python: >=3.7
License-File: LICENSE
Requires-Dist: pysam
Requires-Dist: liqa
Requires-Dist: gffutils
Requires-Dist: pandas
Requires-Dist: biopython
Requires-Dist: lifelines (==0.26.4)
